c4f/__init__.py
c4f/base.py
chat4free/__init__.py
chat4free/base.py
c4f-0.0.0b0.dist-info/LICENSE
c4f-0.0.0b0.dist-info/METADATA
c4f-0.0.0b0.dist-info/WHEEL
c4f-0.0.0b0.dist-info/top_level.txt
c4f-0.0.0b0.dist-info/RECORD
